{
  "produtos": [
    {
      "codigo": "121212651616",
      "nome": "FFWFwf",
      "preco": "14500.00",
      "estoque": "5",
      "vendas": "561",
      "descricao": "/dlfmawlvb",
      "id": 1
    },
    {
      "codigo": "12542",
      "nome": "FFWFwf",
      "preco": "14.00",
      "estoque": "50",
      "vendas": "561",
      "descricao": "teste",
      "id": 2
    },
    {
      "codigo": "12542",
      "nome": "testets",
      "preco": "14.00",
      "estoque": "4",
      "vendas": "50",
      "descricao": "descricao",
      "id": 3
    },
    {
      "codigo": "121212",
      "nome": "FFWFwf",
      "preco": "14000",
      "estoque": "5",
      "vendas": "50",
      "descricao": "ewgwgW",
      "id": 4
    },
    {
      "codigo": "121212",
      "nome": "FFWFwf",
      "preco": "14500.00",
      "estoque": "5",
      "vendas": "561",
      "descricao": "/dlfmawlvb",
      "id": 5
    },
    {
      "codigo": "12542",
      "nome": "FFWFwf",
      "preco": "14.00",
      "estoque": "50",
      "vendas": "561",
      "descricao": "teste",
      "id": 6
    },
    {
      "codigo": "12542",
      "nome": "testets",
      "preco": "14.00",
      "estoque": "4",
      "vendas": "50",
      "descricao": "descricao",
      "id": 7
    },
    {
      "codigo": "121212",
      "nome": "FFWFwf",
      "preco": "14000",
      "estoque": "5",
      "vendas": "50",
      "descricao": "ewgwgW",
      "id": 8
    },
    {
      "codigo": "121212",
      "nome": "FFWFwf",
      "preco": "14500.00",
      "estoque": "5",
      "vendas": "561",
      "descricao": "/dlfmawlvb",
      "id": 9
    },
    {
      "codigo": "12542",
      "nome": "FFWFwf",
      "preco": "14.00",
      "estoque": "50",
      "vendas": "561",
      "descricao": "teste",
      "id": 10
    },
    {
      "codigo": "12542",
      "nome": "testets",
      "preco": "14.00",
      "estoque": "4",
      "vendas": "50",
      "descricao": "descricao",
      "id": 11
    },
    {
      "codigo": "121212",
      "nome": "FFWFwf",
      "preco": "14000",
      "estoque": "5",
      "vendas": "50",
      "descricao": "ewgwgW",
      "id": 12
    },
    {
      "codigo": "121212",
      "nome": "FFWFwf",
      "preco": "14500.00",
      "estoque": "5",
      "vendas": "561",
      "descricao": "/dlfmawlvb",
      "id": 13
    },
    {
      "codigo": "12542",
      "nome": "FFWFwf",
      "preco": "14.00",
      "estoque": "50",
      "vendas": "561",
      "descricao": "teste",
      "id": 14
    },
    {
      "codigo": "12542",
      "nome": "testets",
      "preco": "14.00",
      "estoque": "4",
      "vendas": "50",
      "descricao": "descricao",
      "id": 15
    },
    {
      "codigo": "121212",
      "nome": "FFWFwf",
      "preco": "14000",
      "estoque": "5",
      "vendas": "50",
      "descricao": "ewgwgW",
      "id": 16
    },
    {
      "codigo": "121212",
      "nome": "FFWFwf",
      "preco": "14500.00",
      "estoque": "5",
      "vendas": "561",
      "descricao": "/dlfmawlvb",
      "id": 17
    },
    {
      "codigo": "12542",
      "nome": "FFWFwf",
      "preco": "14.00",
      "estoque": "50",
      "vendas": "561",
      "descricao": "teste",
      "id": 18
    },
    {
      "codigo": "12542",
      "nome": "testets",
      "preco": "14.00",
      "estoque": "4",
      "vendas": "50",
      "descricao": "descricao",
      "id": 19
    },
    {
      "codigo": "121212",
      "nome": "FFWFwf",
      "preco": "14000",
      "estoque": "5",
      "vendas": "50",
      "descricao": "ewgwgW",
      "id": 20
    },
    {
      "0": {
        "codigo": "121212651616",
        "nome": "FFWFwf",
        "preco": "14500.00",
        "estoque": "5",
        "vendas": "561",
        "descricao": "/dlfmawlvb",
        "id": 1
      },
      "1": {
        "codigo": "12542",
        "nome": "FFWFwf",
        "preco": "14.00",
        "estoque": "50",
        "vendas": "561",
        "descricao": "teste",
        "id": 2
      },
      "2": {
        "codigo": "12542",
        "nome": "testets",
        "preco": "14.00",
        "estoque": "4",
        "vendas": "50",
        "descricao": "descricao",
        "id": 3
      },
      "3": {
        "codigo": "121212",
        "nome": "FFWFwf",
        "preco": "14000",
        "estoque": "5",
        "vendas": "50",
        "descricao": "ewgwgW",
        "id": 4
      },
      "4": {
        "codigo": "121212",
        "nome": "FFWFwf",
        "preco": "14500.00",
        "estoque": "5",
        "vendas": "561",
        "descricao": "/dlfmawlvb",
        "id": 5
      },
      "5": {
        "codigo": "12542",
        "nome": "FFWFwf",
        "preco": "14.00",
        "estoque": "50",
        "vendas": "561",
        "descricao": "teste",
        "id": 6
      },
      "6": {
        "codigo": "12542",
        "nome": "testets",
        "preco": "14.00",
        "estoque": "4",
        "vendas": "50",
        "descricao": "descricao",
        "id": 7
      },
      "7": {
        "codigo": "121212",
        "nome": "FFWFwf",
        "preco": "14000",
        "estoque": "5",
        "vendas": "50",
        "descricao": "ewgwgW",
        "id": 8
      },
      "8": {
        "codigo": "121212",
        "nome": "FFWFwf",
        "preco": "14500.00",
        "estoque": "5",
        "vendas": "561",
        "descricao": "/dlfmawlvb",
        "id": 9
      },
      "9": {
        "codigo": "12542",
        "nome": "FFWFwf",
        "preco": "14.00",
        "estoque": "50",
        "vendas": "561",
        "descricao": "teste",
        "id": 10
      },
      "10": {
        "codigo": "12542",
        "nome": "testets",
        "preco": "14.00",
        "estoque": "4",
        "vendas": "50",
        "descricao": "descricao",
        "id": 11
      },
      "11": {
        "codigo": "121212",
        "nome": "FFWFwf",
        "preco": "14000",
        "estoque": "5",
        "vendas": "50",
        "descricao": "ewgwgW",
        "id": 12
      },
      "12": {
        "codigo": "121212",
        "nome": "FFWFwf",
        "preco": "14500.00",
        "estoque": "5",
        "vendas": "561",
        "descricao": "/dlfmawlvb",
        "id": 13
      },
      "13": {
        "codigo": "12542",
        "nome": "FFWFwf",
        "preco": "14.00",
        "estoque": "50",
        "vendas": "561",
        "descricao": "teste",
        "id": 14
      },
      "14": {
        "codigo": "12542",
        "nome": "testets",
        "preco": "14.00",
        "estoque": "4",
        "vendas": "50",
        "descricao": "descricao",
        "id": 15
      },
      "15": {
        "codigo": "121212",
        "nome": "FFWFwf",
        "preco": "14000",
        "estoque": "5",
        "vendas": "50",
        "descricao": "ewgwgW",
        "id": 16
      },
      "16": {
        "codigo": "121212",
        "nome": "FFWFwf",
        "preco": "14500.00",
        "estoque": "5",
        "vendas": "561",
        "descricao": "/dlfmawlvb",
        "id": 17
      },
      "17": {
        "codigo": "12542",
        "nome": "FFWFwf",
        "preco": "14.00",
        "estoque": "50",
        "vendas": "561",
        "descricao": "teste",
        "id": 18
      },
      "18": {
        "codigo": "12542",
        "nome": "testets",
        "preco": "14.00",
        "estoque": "4",
        "vendas": "50",
        "descricao": "descricao",
        "id": 19
      },
      "19": {
        "codigo": "121212",
        "nome": "FFWFwf",
        "preco": "14000",
        "estoque": "5",
        "vendas": "50",
        "descricao": "ewgwgW",
        "id": 20
      },
      "codigo": "121212651616",
      "nome": "FFWFwf",
      "preco": "14.00",
      "estoque": "5",
      "vendas": "561",
      "descricao": "produto incrivelwcvwv",
      "id": 21
    },
    {
      "0": {
        "codigo": "121212651616",
        "nome": "FFWFwf",
        "preco": "14500.00",
        "estoque": "5",
        "vendas": "561",
        "descricao": "/dlfmawlvb",
        "id": 1
      },
      "1": {
        "codigo": "12542",
        "nome": "FFWFwf",
        "preco": "14.00",
        "estoque": "50",
        "vendas": "561",
        "descricao": "teste",
        "id": 2
      },
      "2": {
        "codigo": "12542",
        "nome": "testets",
        "preco": "14.00",
        "estoque": "4",
        "vendas": "50",
        "descricao": "descricao",
        "id": 3
      },
      "3": {
        "codigo": "121212",
        "nome": "FFWFwf",
        "preco": "14000",
        "estoque": "5",
        "vendas": "50",
        "descricao": "ewgwgW",
        "id": 4
      },
      "4": {
        "codigo": "121212",
        "nome": "FFWFwf",
        "preco": "14500.00",
        "estoque": "5",
        "vendas": "561",
        "descricao": "/dlfmawlvb",
        "id": 5
      },
      "5": {
        "codigo": "12542",
        "nome": "FFWFwf",
        "preco": "14.00",
        "estoque": "50",
        "vendas": "561",
        "descricao": "teste",
        "id": 6
      },
      "6": {
        "codigo": "12542",
        "nome": "testets",
        "preco": "14.00",
        "estoque": "4",
        "vendas": "50",
        "descricao": "descricao",
        "id": 7
      },
      "7": {
        "codigo": "121212",
        "nome": "FFWFwf",
        "preco": "14000",
        "estoque": "5",
        "vendas": "50",
        "descricao": "ewgwgW",
        "id": 8
      },
      "8": {
        "codigo": "121212",
        "nome": "FFWFwf",
        "preco": "14500.00",
        "estoque": "5",
        "vendas": "561",
        "descricao": "/dlfmawlvb",
        "id": 9
      },
      "9": {
        "codigo": "12542",
        "nome": "FFWFwf",
        "preco": "14.00",
        "estoque": "50",
        "vendas": "561",
        "descricao": "teste",
        "id": 10
      },
      "10": {
        "codigo": "12542",
        "nome": "testets",
        "preco": "14.00",
        "estoque": "4",
        "vendas": "50",
        "descricao": "descricao",
        "id": 11
      },
      "11": {
        "codigo": "121212",
        "nome": "FFWFwf",
        "preco": "14000",
        "estoque": "5",
        "vendas": "50",
        "descricao": "ewgwgW",
        "id": 12
      },
      "12": {
        "codigo": "121212",
        "nome": "FFWFwf",
        "preco": "14500.00",
        "estoque": "5",
        "vendas": "561",
        "descricao": "/dlfmawlvb",
        "id": 13
      },
      "13": {
        "codigo": "12542",
        "nome": "FFWFwf",
        "preco": "14.00",
        "estoque": "50",
        "vendas": "561",
        "descricao": "teste",
        "id": 14
      },
      "14": {
        "codigo": "12542",
        "nome": "testets",
        "preco": "14.00",
        "estoque": "4",
        "vendas": "50",
        "descricao": "descricao",
        "id": 15
      },
      "15": {
        "codigo": "121212",
        "nome": "FFWFwf",
        "preco": "14000",
        "estoque": "5",
        "vendas": "50",
        "descricao": "ewgwgW",
        "id": 16
      },
      "16": {
        "codigo": "121212",
        "nome": "FFWFwf",
        "preco": "14500.00",
        "estoque": "5",
        "vendas": "561",
        "descricao": "/dlfmawlvb",
        "id": 17
      },
      "17": {
        "codigo": "12542",
        "nome": "FFWFwf",
        "preco": "14.00",
        "estoque": "50",
        "vendas": "561",
        "descricao": "teste",
        "id": 18
      },
      "18": {
        "codigo": "12542",
        "nome": "testets",
        "preco": "14.00",
        "estoque": "4",
        "vendas": "50",
        "descricao": "descricao",
        "id": 19
      },
      "19": {
        "codigo": "121212",
        "nome": "FFWFwf",
        "preco": "14000",
        "estoque": "5",
        "vendas": "50",
        "descricao": "ewgwgW",
        "id": 20
      },
      "20": {
        "0": {
          "codigo": "121212651616",
          "nome": "FFWFwf",
          "preco": "14500.00",
          "estoque": "5",
          "vendas": "561",
          "descricao": "/dlfmawlvb",
          "id": 1
        },
        "1": {
          "codigo": "12542",
          "nome": "FFWFwf",
          "preco": "14.00",
          "estoque": "50",
          "vendas": "561",
          "descricao": "teste",
          "id": 2
        },
        "2": {
          "codigo": "12542",
          "nome": "testets",
          "preco": "14.00",
          "estoque": "4",
          "vendas": "50",
          "descricao": "descricao",
          "id": 3
        },
        "3": {
          "codigo": "121212",
          "nome": "FFWFwf",
          "preco": "14000",
          "estoque": "5",
          "vendas": "50",
          "descricao": "ewgwgW",
          "id": 4
        },
        "4": {
          "codigo": "121212",
          "nome": "FFWFwf",
          "preco": "14500.00",
          "estoque": "5",
          "vendas": "561",
          "descricao": "/dlfmawlvb",
          "id": 5
        },
        "5": {
          "codigo": "12542",
          "nome": "FFWFwf",
          "preco": "14.00",
          "estoque": "50",
          "vendas": "561",
          "descricao": "teste",
          "id": 6
        },
        "6": {
          "codigo": "12542",
          "nome": "testets",
          "preco": "14.00",
          "estoque": "4",
          "vendas": "50",
          "descricao": "descricao",
          "id": 7
        },
        "7": {
          "codigo": "121212",
          "nome": "FFWFwf",
          "preco": "14000",
          "estoque": "5",
          "vendas": "50",
          "descricao": "ewgwgW",
          "id": 8
        },
        "8": {
          "codigo": "121212",
          "nome": "FFWFwf",
          "preco": "14500.00",
          "estoque": "5",
          "vendas": "561",
          "descricao": "/dlfmawlvb",
          "id": 9
        },
        "9": {
          "codigo": "12542",
          "nome": "FFWFwf",
          "preco": "14.00",
          "estoque": "50",
          "vendas": "561",
          "descricao": "teste",
          "id": 10
        },
        "10": {
          "codigo": "12542",
          "nome": "testets",
          "preco": "14.00",
          "estoque": "4",
          "vendas": "50",
          "descricao": "descricao",
          "id": 11
        },
        "11": {
          "codigo": "121212",
          "nome": "FFWFwf",
          "preco": "14000",
          "estoque": "5",
          "vendas": "50",
          "descricao": "ewgwgW",
          "id": 12
        },
        "12": {
          "codigo": "121212",
          "nome": "FFWFwf",
          "preco": "14500.00",
          "estoque": "5",
          "vendas": "561",
          "descricao": "/dlfmawlvb",
          "id": 13
        },
        "13": {
          "codigo": "12542",
          "nome": "FFWFwf",
          "preco": "14.00",
          "estoque": "50",
          "vendas": "561",
          "descricao": "teste",
          "id": 14
        },
        "14": {
          "codigo": "12542",
          "nome": "testets",
          "preco": "14.00",
          "estoque": "4",
          "vendas": "50",
          "descricao": "descricao",
          "id": 15
        },
        "15": {
          "codigo": "121212",
          "nome": "FFWFwf",
          "preco": "14000",
          "estoque": "5",
          "vendas": "50",
          "descricao": "ewgwgW",
          "id": 16
        },
        "16": {
          "codigo": "121212",
          "nome": "FFWFwf",
          "preco": "14500.00",
          "estoque": "5",
          "vendas": "561",
          "descricao": "/dlfmawlvb",
          "id": 17
        },
        "17": {
          "codigo": "12542",
          "nome": "FFWFwf",
          "preco": "14.00",
          "estoque": "50",
          "vendas": "561",
          "descricao": "teste",
          "id": 18
        },
        "18": {
          "codigo": "12542",
          "nome": "testets",
          "preco": "14.00",
          "estoque": "4",
          "vendas": "50",
          "descricao": "descricao",
          "id": 19
        },
        "19": {
          "codigo": "121212",
          "nome": "FFWFwf",
          "preco": "14000",
          "estoque": "5",
          "vendas": "50",
          "descricao": "ewgwgW",
          "id": 20
        },
        "codigo": "121212651616",
        "nome": "FFWFwf",
        "preco": "14.00",
        "estoque": "5",
        "vendas": "561",
        "descricao": "produto incrivelwcvwv",
        "id": 21
      },
      "codigo": "121212651616",
      "nome": "FFWFwf",
      "preco": "14.00",
      "estoque": "5",
      "vendas": "50",
      "descricao": "dadf",
      "id": 22
    }
  ]
}